langchain_pull_md/__init__.py
langchain_pull_md/markdown_loader.py
langchain_pull_md-0.1.2.dist-info/METADATA
langchain_pull_md-0.1.2.dist-info/WHEEL
langchain_pull_md-0.1.2.dist-info/licenses/LICENSE
langchain_pull_md-0.1.2.dist-info/RECORD
