Metadata-Version: 2.4
Name: langchain-pull-md
Version: 0.1.2
Summary: langchain-pull-md is a Python package that extends LangChain with a loader to convert URLs into Markdown. It addresses the challenge of extracting content from JavaScript-rendered pages, like those built with React, Angular, or Vue.js, by utilizing the pull.md service. This approach optimizes resource usage and ensures efficient, reliable Markdown conversion directly from URLs.
License: Apache-2.0
License-File: LICENSE
Author: E. Evstafev
Author-email: chigwel@gmail.com
Requires-Python: >=3.10.15,<4.0.0
Classifier: License :: OSI Approved :: Apache Software License
Classifier: Programming Language :: Python :: 3
Classifier: Programming Language :: Python :: 3.11
Classifier: Programming Language :: Python :: 3.12
Classifier: Programming Language :: Python :: 3.13
Classifier: Programming Language :: Python :: 3.14
Requires-Dist: requests (>=2.25.1)
